{"today": [{"id": 9008, "date": "2022-06-11 14:30", "home_team": "HC Sintra", "away_team": "APAC Tojal", "url": "https://fpp.assyssoftware.es/intranet/web/partido.asp?id=7367", "competition": "Campeonato Nacional de Sub-15 - Sul"}, {"id": 9041, "date": "2022-06-11 18:00", "home_team": "HC Turquel", "away_team": "FC Alverca", "url": "https://fpp.assyssoftware.es/intranet/web/partido.asp?id=7590", "competition": "Campeonato Nacional de Sub-13 - Sul"}, {"id": 9049, "date": "2022-06-11 15:00", "home_team": "UD Oliveirense", "away_team": "ACD Gulpilhares", "url": "https://fpp.assyssoftware.es/intranet/web/partido.asp?id=7424", "competition": "Campeonato Nacional de Sub-17 - Norte"}, {"id": 9050, "date": "2022-06-11 17:30", "home_team": "AD Valongo", "away_team": "FC Porto", "url": "https://fpp.assyssoftware.es/intranet/web/partido.asp?id=7425", "competition": "Campeonato Nacional de Sub-17 - Norte"}, {"id": 9057, "date": "2022-06-11 18:00", "home_team": "Parede FC", "away_team": "Sporting CP", "url": "https://fpp.assyssoftware.es/intranet/web/partido.asp?id=7479", "competition": "Campeonato Nacional de Sub-17 - Sul"}, {"id": 9064, "date": "2022-06-11 19:00", "home_team": "GRF Murches", "away_team": "Famalicense AC", "url": "https://fpp.assyssoftware.es/intranet/web/partido.asp?id=7699", "competition": "2\u00aa Divis\u00e3o Apuramento Campe\u00e3o"}, {"id": 9065, "date": "2022-06-11 18:30", "home_team": "Riba d' Ave HC", "away_team": "S Alenquer B", "url": "https://fpp.assyssoftware.es/intranet/web/partido.asp?id=7697", "competition": "2\u00aa Divis\u00e3o Apuramento Promo\u00e7\u00e3o"}, {"id": 9066, "date": "2022-06-11 18:30", "home_team": "Escola Livre A", "away_team": "Sporting CP B", "url": "https://fpp.assyssoftware.es/intranet/web/partido.asp?id=7720", "competition": "3\u00aa Divis\u00e3o Apuramento Campe\u00e3o"}], "tomorrow": [{"id": 8995, "date": "2022-06-12 18:30", "home_team": "Sporting CP", "away_team": "SL Benfica", "url": "https://fpp.assyssoftware.es/intranet/web/partido.asp?id=7706", "competition": "CN I Divis\u00e3o - Play Off - 1/2 de Final"}, {"id": 8996, "date": "2022-06-12 11:00", "home_team": "SL Benfica", "away_team": "CA Campo Ourique", "url": "https://fpp.assyssoftware.es/intranet/web/partido.asp?id=7713", "competition": "CN Seniores Feminino - Fase 3 - Apuramento Campe\u00e3o- Play Off - 1/2 Final"}, {"id": 8997, "date": "2022-06-12 12:00", "home_team": "Sporting CP", "away_team": "CA Feira", "url": "https://fpp.assyssoftware.es/intranet/web/partido.asp?id=7742", "competition": "CN Seniores Feminino - Fase 3 - Apuramento Campe\u00e3o- Play Off - 1/2 Final"}, {"id": 9000, "date": "2022-06-12 18:00", "home_team": "ACD Gulpilhares", "away_team": "USC Paredes", "url": "https://fpp.assyssoftware.es/intranet/web/partido.asp?id=7314", "competition": "Campeonato Nacional de Sub-15 - Norte"}, {"id": 9001, "date": "2022-06-12 15:00", "home_team": "C Infante Sagres", "away_team": "HC Braga", "url": "https://fpp.assyssoftware.es/intranet/web/partido.asp?id=7315", "competition": "Campeonato Nacional de Sub-15 - Norte"}, {"id": 9002, "date": "2022-06-12 15:00", "home_team": "UD Oliveirense", "away_team": "FC Porto", "url": "https://fpp.assyssoftware.es/intranet/web/partido.asp?id=7316", "competition": "Campeonato Nacional de Sub-15 - Norte"}, {"id": 9003, "date": "2022-06-12 15:00", "home_team": "AD Valongo", "away_team": "HA Cambra", "url": "https://fpp.assyssoftware.es/intranet/web/partido.asp?id=7317", "competition": "Campeonato Nacional de Sub-15 - Norte"}, {"id": 9009, "date": "2022-06-12 15:00", "home_team": "HCP Gr\u00e2ndola", "away_team": "AD Oeiras", "url": "https://fpp.assyssoftware.es/intranet/web/partido.asp?id=7370", "competition": "Campeonato Nacional de Sub-15 - Sul"}, {"id": 9010, "date": "2022-06-12 18:15", "home_team": "HC Turquel", "away_team": "HC Sintra", "url": "https://fpp.assyssoftware.es/intranet/web/partido.asp?id=7371", "competition": "Campeonato Nacional de Sub-15 - Sul"}, {"id": 9011, "date": "2022-06-12 16:00", "home_team": "APAC Tojal", "away_team": "AE Fisica D", "url": "https://fpp.assyssoftware.es/intranet/web/partido.asp?id=7372", "competition": "Campeonato Nacional de Sub-15 - Sul"}, {"id": 9012, "date": "2022-06-12 17:30", "home_team": "Sporting CP", "away_team": "SL Benfica", "url": "https://fpp.assyssoftware.es/intranet/web/partido.asp?id=7373", "competition": "Campeonato Nacional de Sub-15 - Sul"}, {"id": 9017, "date": "2022-06-12 17:00", "home_team": "SC Tomar", "away_team": "Riba d' Ave HC", "url": "https://fpp.assyssoftware.es/intranet/web/partido.asp?id=7203", "competition": "Campeonato Nacional de Sub-19 - Norte"}, {"id": 9018, "date": "2022-06-12 17:30", "home_team": "OC Barcelos", "away_team": "FC Porto", "url": "https://fpp.assyssoftware.es/intranet/web/partido.asp?id=7204", "competition": "Campeonato Nacional de Sub-19 - Norte"}, {"id": 9019, "date": "2022-06-12 20:00", "home_team": "AD Valongo", "away_team": "UD Oliveirense", "url": "https://fpp.assyssoftware.es/intranet/web/partido.asp?id=7205", "competition": "Campeonato Nacional de Sub-19 - Norte"}, {"id": 9025, "date": "2022-06-12 18:00", "home_team": "HCP Gr\u00e2ndola", "away_team": "FC Alverca", "url": "https://fpp.assyssoftware.es/intranet/web/partido.asp?id=7258", "competition": "Campeonato Nacional de Sub-19 - Sul"}, {"id": 9026, "date": "2022-06-12 17:00", "home_team": "S Alenquer B", "away_team": "CD Pa\u00e7o Arcos", "url": "https://fpp.assyssoftware.es/intranet/web/partido.asp?id=7259", "competition": "Campeonato Nacional de Sub-19 - Sul"}, {"id": 9027, "date": "2022-06-12 18:00", "home_team": "Parede FC", "away_team": "Sporting CP", "url": "https://fpp.assyssoftware.es/intranet/web/partido.asp?id=7260", "competition": "Campeonato Nacional de Sub-19 - Sul"}, {"id": 9028, "date": "2022-06-12 12:00", "home_team": "HC Turquel", "away_team": "SL Benfica", "url": "https://fpp.assyssoftware.es/intranet/web/partido.asp?id=7261", "competition": "Campeonato Nacional de Sub-19 - Sul"}, {"id": 9033, "date": "2022-06-12 15:00", "home_team": "HC Penafiel", "away_team": "HC Braga", "url": "https://fpp.assyssoftware.es/intranet/web/partido.asp?id=7535", "competition": "Campeonato Nacional de Sub-13 - Norte"}, {"id": 9034, "date": "2022-06-12 15:30", "home_team": "HC Mealhada", "away_team": "FC Porto", "url": "https://fpp.assyssoftware.es/intranet/web/partido.asp?id=7536", "competition": "Campeonato Nacional de Sub-13 - Norte"}, {"id": 9035, "date": "2022-06-12 17:30", "home_team": "UD Oliveirense", "away_team": "C Infante Sagres", "url": "https://fpp.assyssoftware.es/intranet/web/partido.asp?id=7537", "competition": "Campeonato Nacional de Sub-13 - Norte"}, {"id": 9042, "date": "2022-06-12 15:00", "home_team": "Sporting CP", "away_team": "HC Sintra", "url": "https://fpp.assyssoftware.es/intranet/web/partido.asp?id=7592", "competition": "Campeonato Nacional de Sub-13 - Sul"}, {"id": 9043, "date": "2022-06-12 16:00", "home_team": "GD Fabril", "away_team": "CD Pa\u00e7o Arcos", "url": "https://fpp.assyssoftware.es/intranet/web/partido.asp?id=7593", "competition": "Campeonato Nacional de Sub-13 - Sul"}, {"id": 9051, "date": "2022-06-12 17:30", "home_team": "C Infante Sagres", "away_team": "HC Mealhada", "url": "https://fpp.assyssoftware.es/intranet/web/partido.asp?id=7422", "competition": "Campeonato Nacional de Sub-17 - Norte"}, {"id": 9052, "date": "2022-06-12 18:00", "home_team": "AD Barcelos/Campo", "away_team": "OC Barcelos", "url": "https://fpp.assyssoftware.es/intranet/web/partido.asp?id=7423", "competition": "Campeonato Nacional de Sub-17 - Norte"}, {"id": 9058, "date": "2022-06-12 16:30", "home_team": "GD Sesimbra", "away_team": "CD Pa\u00e7o Arcos", "url": "https://fpp.assyssoftware.es/intranet/web/partido.asp?id=7481", "competition": "Campeonato Nacional de Sub-17 - Sul"}, {"id": 9067, "date": "2022-06-12 17:30", "home_team": "AD Valongo \"B\"", "away_team": "UF Entroncamento", "url": "https://fpp.assyssoftware.es/intranet/web/partido.asp?id=7719", "competition": "3\u00aa Divis\u00e3o Apuramento Campe\u00e3o"}, {"id": 9070, "date": "2022-06-12 16:00", "home_team": "USC Paredes/Maximus 17", "away_team": "CA Campo Ourique", "url": "https://fpp.assyssoftware.es/intranet/web/partido.asp?id=7731", "competition": "3\u00aa Divis\u00e3o Apuramento Promo\u00e7\u00e3o"}, {"id": 9071, "date": "2022-06-12 18:00", "home_team": "SC Leiria e Marrazes", "away_team": "GDC F\u00e2nzeres", "url": "https://fpp.assyssoftware.es/intranet/web/partido.asp?id=7732", "competition": "3\u00aa Divis\u00e3o Apuramento Promo\u00e7\u00e3o"}]}